LICENCE
README.md
setup.py
inference_causal/__init__.py
inference_causal/pareamento.py
inference_causal.egg-info/PKG-INFO
inference_causal.egg-info/SOURCES.txt
inference_causal.egg-info/dependency_links.txt
inference_causal.egg-info/requires.txt
inference_causal.egg-info/top_level.txt