Metadata-Version: 2.1
Name: inference-causal
Version: 0.1.0
Summary: Tecnicas de inferencia
Author: Kleber Jorge Santos
License: MIT License
Keywords: logistic,regression,matching,observational,study,causal,inference
License-File: LICENCE
